<annotation>
  <folder>VOC2007</folder>
  <filename>123.jpg</filename>
  <source>
    <database>Self-made database</database>
  </source>
  <size>
    <width>640</width>
    <height>640</height>
    <depth>3</depth>
  </size>
  <segmented>0</segmented>
  <object>
    <name>Aruco</name>
    <pose>Unspecified</pose>
    <truncated>0</truncated>
    <difficult>0</difficult>
    <bndbox>
      <xmin>362</xmin>
      <ymin>209</ymin>
      <xmax>504</xmax>
      <ymax>351</ymax>
    </bndbox>
  </object>
  <object>
    <name>Chemical_Sign</name>
    <pose>Unspecified</pose>
    <truncated>0</truncated>
    <difficult>0</difficult>
    <bndbox>
      <xmin>12</xmin>
      <ymin>434</ymin>
      <xmax>125</xmax>
      <ymax>547</ymax>
    </bndbox>
  </object>
</annotation>