<annotation>
  <folder>VOC2007</folder>
  <filename>2013.jpg</filename>
  <source>
    <database>Self-made database</database>
  </source>
  <size>
    <width>640</width>
    <height>640</height>
    <depth>3</depth>
  </size>
  <segmented>0</segmented>
  <object>
    <name>Dangerous_Goods</name>
    <pose>Unspecified</pose>
    <truncated>0</truncated>
    <difficult>0</difficult>
    <bndbox>
      <xmin>333</xmin>
      <ymin>64</ymin>
      <xmax>461</xmax>
      <ymax>192</ymax>
    </bndbox>
  </object>
  <object>
    <name>Dangerous_Goods</name>
    <pose>Unspecified</pose>
    <truncated>0</truncated>
    <difficult>0</difficult>
    <bndbox>
      <xmin>508</xmin>
      <ymin>251</ymin>
      <xmax>608</xmax>
      <ymax>351</ymax>
    </bndbox>
  </object>
</annotation>