<annotation>
  <folder>VOC2007</folder>
  <filename>2274.jpg</filename>
  <source>
    <database>Self-made database</database>
  </source>
  <size>
    <width>640</width>
    <height>640</height>
    <depth>3</depth>
  </size>
  <segmented>0</segmented>
  <object>
    <name>Dangerous_Goods</name>
    <pose>Unspecified</pose>
    <truncated>0</truncated>
    <difficult>0</difficult>
    <bndbox>
      <xmin>438</xmin>
      <ymin>68</ymin>
      <xmax>561</xmax>
      <ymax>191</ymax>
    </bndbox>
  </object>
  <object>
    <name>Chemical_Sign</name>
    <pose>Unspecified</pose>
    <truncated>0</truncated>
    <difficult>0</difficult>
    <bndbox>
      <xmin>217</xmin>
      <ymin>233</ymin>
      <xmax>331</xmax>
      <ymax>347</ymax>
    </bndbox>
  </object>
</annotation>