<annotation>
  <folder>VOC2007</folder>
  <filename>2497.jpg</filename>
  <source>
    <database>Self-made database</database>
  </source>
  <size>
    <width>640</width>
    <height>640</height>
    <depth>3</depth>
  </size>
  <segmented>0</segmented>
  <object>
    <name>Chemical_Sign</name>
    <pose>Unspecified</pose>
    <truncated>0</truncated>
    <difficult>0</difficult>
    <bndbox>
      <xmin>471</xmin>
      <ymin>339</ymin>
      <xmax>632</xmax>
      <ymax>507</ymax>
    </bndbox>
  </object>
  <object>
    <name>Dangerous_Goods</name>
    <pose>Unspecified</pose>
    <truncated>0</truncated>
    <difficult>0</difficult>
    <bndbox>
      <xmin>178</xmin>
      <ymin>592</ymin>
      <xmax>192</xmax>
      <ymax>607</ymax>
    </bndbox>
  </object>
  <object>
    <name>Chemical_Sign</name>
    <pose>Unspecified</pose>
    <truncated>0</truncated>
    <difficult>0</difficult>
    <bndbox>
      <xmin>166</xmin>
      <ymin>554</ymin>
      <xmax>272</xmax>
      <ymax>639</ymax>
    </bndbox>
  </object>
</annotation>