<annotation>
  <folder>VOC2007</folder>
  <filename>2511.jpg</filename>
  <source>
    <database>Self-made database</database>
  </source>
  <size>
    <width>640</width>
    <height>640</height>
    <depth>3</depth>
  </size>
  <segmented>0</segmented>
  <object>
    <name>Chemical_Sign</name>
    <pose>Unspecified</pose>
    <truncated>0</truncated>
    <difficult>0</difficult>
    <bndbox>
      <xmin>96</xmin>
      <ymin>508</ymin>
      <xmax>218</xmax>
      <ymax>630</ymax>
    </bndbox>
  </object>
  <object>
    <name>Dangerous_Goods</name>
    <pose>Unspecified</pose>
    <truncated>0</truncated>
    <difficult>0</difficult>
    <bndbox>
      <xmin>426</xmin>
      <ymin>397</ymin>
      <xmax>531</xmax>
      <ymax>502</ymax>
    </bndbox>
  </object>
  <object>
    <name>Chemical_Sign</name>
    <pose>Unspecified</pose>
    <truncated>0</truncated>
    <difficult>0</difficult>
    <bndbox>
      <xmin>277</xmin>
      <ymin>532</ymin>
      <xmax>361</xmax>
      <ymax>616</ymax>
    </bndbox>
  </object>
</annotation>