<annotation>
  <folder>VOC2007</folder>
  <filename>2634.jpg</filename>
  <source>
    <database>Self-made database</database>
  </source>
  <size>
    <width>1000</width>
    <height>1000</height>
    <depth>3</depth>
  </size>
  <segmented>0</segmented>
  <object>
    <name>Chemical_Sign</name>
    <pose>Unspecified</pose>
    <truncated>0</truncated>
    <difficult>0</difficult>
    <bndbox>
      <xmin>60</xmin>
      <ymin>656</ymin>
      <xmax>311</xmax>
      <ymax>907</ymax>
    </bndbox>
  </object>
  <object>
    <name>Chemical_Sign</name>
    <pose>Unspecified</pose>
    <truncated>0</truncated>
    <difficult>0</difficult>
    <bndbox>
      <xmin>511</xmin>
      <ymin>616</ymin>
      <xmax>740</xmax>
      <ymax>845</ymax>
    </bndbox>
  </object>
</annotation>